graphscope_runtime/__init__.py
gs_include-0.20.0.dist-info/RECORD
gs_include-0.20.0.dist-info/WHEEL
gs_include-0.20.0.dist-info/top_level.txt
gs_include-0.20.0.dist-info/METADATA
graphscope.runtime/include/graphscope/core/error.h
graphscope.runtime/include/graphscope/core/config.h
graphscope.runtime/include/graphscope/core/flags.h
graphscope.runtime/include/graphscope/core/launcher.h
graphscope.runtime/include/graphscope/core/grape_instance.h
graphscope.runtime/include/graphscope/core/parallel/thread_local_property_message_buffer.h
graphscope.runtime/include/graphscope/core/parallel/property_auto_message_manager.h
graphscope.runtime/include/graphscope/core/parallel/property_message_manager.h
graphscope.runtime/include/graphscope/core/parallel/parallel_property_message_manager.h
graphscope.runtime/include/graphscope/core/context/java_context_base.h
graphscope.runtime/include/graphscope/core/context/selector.h
graphscope.runtime/include/graphscope/core/context/vertex_data_context.h
graphscope.runtime/include/graphscope/core/context/java_pie_property_context.h
graphscope.runtime/include/graphscope/core/context/java_pie_projected_context.h
graphscope.runtime/include/graphscope/core/context/context_protocols.h
graphscope.runtime/include/graphscope/core/context/vertex_property_context.h
graphscope.runtime/include/graphscope/core/context/mpi_object_sync.h
graphscope.runtime/include/graphscope/core/context/column.h
graphscope.runtime/include/graphscope/core/context/tensor_context.h
graphscope.runtime/include/graphscope/core/context/i_context.h
graphscope.runtime/include/graphscope/core/context/tensor_dataframe_builder.h
graphscope.runtime/include/graphscope/core/context/labeled_vertex_property_context.h
graphscope.runtime/include/graphscope/core/vertex_map/extra_vertex_map.h
graphscope.runtime/include/graphscope/core/vertex_map/arrow_projected_vertex_map.h
graphscope.runtime/include/graphscope/core/vertex_map/global_vertex_map.h
graphscope.runtime/include/graphscope/core/app/property_app_base.h
graphscope.runtime/include/graphscope/core/app/parallel_property_app_base.h
